nlon_py/__init__.py
nlon_py/cli.py
nlon_py/features.py
nlon_py/model.py
nlon_py/nlon_py.py
nlon_py/data/bitcoin.csv
nlon_py/data/build_model.py
nlon_py/data/default_data.joblib
nlon_py/data/default_model.joblib
nlon_py/data/default_vectorizer.joblib
nlon_py/data/kubernetes.csv
nlon_py/data/lines.10k.cfo.sample.2000 - Bitcoin (github.com).csv
nlon_py/data/lines.10k.cfo.sample.2000 - Kubernetes (Slackarchive.io).csv
nlon_py/data/lines.10k.cfo.sample.2000 - Lucene-dev mailing list.csv
"nlon_py/data/lines.10k.cfo.sample.2000 - Mozilla (Firefox, Core, OS).csv"
nlon_py/data/lucene.csv
nlon_py/data/make_data.py
nlon_py/data/mozilla.csv
nlon_py/data/mysql_sw_wo_code_words.txt
nlon_py-0.1.5.dist-info/AUTHORS.rst
nlon_py-0.1.5.dist-info/LICENSE
nlon_py-0.1.5.dist-info/METADATA
nlon_py-0.1.5.dist-info/WHEEL
nlon_py-0.1.5.dist-info/entry_points.txt
nlon_py-0.1.5.dist-info/top_level.txt
nlon_py-0.1.5.dist-info/RECORD
